{
    "index": {
        "title": "RECOM Metal Duro | Distribuidor Mitsubishi Materials em Campinas",
        "description": "Distribuidor autorizado de ferramentas de corte Mitsubishi Materials, 7Leaders e BT Fixo. Soluções técnicas para usinagem em Campinas e região.",
        "h1": "Soluções em Ferramentas de Corte e Usinagem"
    },
    "fornecedores": {
        "title": "Nossos Fornecedores de Ferramentas de Corte | RECOM",
        "description": "Confira os catálogos oficiais da Mitsubishi Materials, 7Leaders, BT Fixo e Kifix. Distribuição autorizada RECOM Metal Duro.",
        "h1": "Marcas e Catálogos Oficiais"
    },
    "processos": {
        "title": "Processos de Usinagem e Soluções Técnicas | RECOM",
        "description": "Especialistas em torneamento, fresamento e furação. Consultoria técnica para otimização de processos industriais.",
        "h1": "Processos & Aplicações"
    },
    "sobre": {
        "title": "Sobre a RECOM Metal Duro | Tradição em Usinagem desde 1991",
        "description": "Conheça a história da RECOM, parceira técnica das maiores indústrias de Campinas e região há mais de 30 anos.",
        "h1": "Nossa História e Compromisso"
    },
    "contato": {
        "title": "Solicitar Orçamento de Ferramentas | Contato RECOM",
        "description": "Envie sua solicitação de orçamento ou suporte técnico para a RECOM Metal Duro. Atendimento especializado B2B.",
        "h1": "Contato / Orçamento"
    },
    "promocoes": {
        "title": "Promoções e Lotes Especiais | RECOM Metal Duro",
        "description": "Confira as ofertas vigentes e lotes promocionais de ferramentas de corte. Oportunidades por tempo limitado.",
        "h1": "Promoções Ativas"
    }
}
